<?xml version="1.0" encoding="UTF-8"?>
<!DOCTYPE collection SYSTEM "BioC.dtd">
<collection>
  <source>PubTator</source>
  <date/>
  <key>BioC.key</key>
  <document>
    <id>30857629</id>
    <infon key="tt_curatable">no</infon>
    <infon key="tt_version">0</infon>
    <infon key="tt_round">0</infon>
    <passage>
      <infon key="type">title</infon>
      <offset>0</offset>
      <text>Molecular characterization of glutamate-gated chloride channel and its possible roles in development and abamectin susceptibility in the rice stem borer, Chilo suppressalis.</text>
      <annotation id="1">
        <infon key="identifier"></infon>
        <infon key="type">Gene</infon>
        <infon key="updated_at">1980-01-01T00:00:00Z</infon>
        <location offset="30" length="32"/>
        <text>glutamate-gated chloride channel</text>
      </annotation>
      <annotation id="2">
        <infon key="identifier">4530</infon>
        <infon key="type">Species</infon>
        <infon key="updated_at">1980-01-01T00:00:00Z</infon>
        <location offset="137" length="4"/>
        <text>rice</text>
      </annotation>
      <annotation id="3">
        <infon key="identifier">168631</infon>
        <infon key="type">Species</infon>
        <infon key="updated_at">1980-01-01T00:00:00Z</infon>
        <location offset="154" length="18"/>
        <text>Chilo suppressalis</text>
      </annotation>
    </passage>
    <passage>
      <infon key="type">abstract</infon>
      <offset>174</offset>
      <text>Glutamate-gated chloride channels (GluCls) mediate fast inhibitory neurotransmission in invertebrate nervous systems, and are of considerable interest in insecticide discovery. The full length cDNA encoding CsGluCl was cloned from the rice stem borer Chilo suppressalis (Walker). Multiple cDNA sequence alignment revealed three variants of CsGluCl generated by alternative splicing of exon 3 and exon 9. While all the transcripts were predominantly expressed in both nerve cord and brain, the expression patterns of these three variants differed among other tissues and developmental stages. Specifically, the expression level of CsGluCl C in cuticle was similar to that in nerve cord and brain, and was the predominant variant in late pupae and early adult stages. Both injection and oral delivery of dsGluCl significantly reduced the mRNA level of CsGluCl. Increased susceptibility to abamectin and reduced larvae growth and pupation rate were observed in dsGluCl-treated larvae. Thus, our results provide the evidence that in addition to act as the target of abamectin, GluCls also play important physiological roles in the development of insects.</text>
      <annotation id="14">
        <infon key="type">Gene</infon>
        <infon key="identifier"></infon>
        <infon key="annotator">5ef4bd7e0113</infon>
        <infon key="updated_at">2020-05-27T18:34:28Z</infon>
        <location offset="174" length="32"/>
        <text>Glutamate-gated chloride channel</text>
      </annotation>
      <annotation id="6">
        <infon key="identifier"></infon>
        <infon key="type">Gene</infon>
        <infon key="updated_at">1980-01-01T00:00:00Z</infon>
        <location offset="209" length="5"/>
        <text>GluCl</text>
      </annotation>
      <annotation id="7">
        <infon key="identifier"></infon>
        <infon key="type">Gene</infon>
        <infon key="updated_at">1980-01-01T00:00:00Z</infon>
        <location offset="381" length="7"/>
        <text>CsGluCl</text>
      </annotation>
      <annotation id="15">
        <infon key="type">Species</infon>
        <infon key="identifier"></infon>
        <infon key="annotator">5ef4bd7e0113</infon>
        <infon key="updated_at">2020-05-27T18:34:48Z</infon>
        <location offset="409" length="15"/>
        <text>rice stem borer</text>
      </annotation>
      <annotation id="9">
        <infon key="identifier">168631</infon>
        <infon key="type">Species</infon>
        <infon key="updated_at">1980-01-01T00:00:00Z</infon>
        <location offset="425" length="18"/>
        <text>Chilo suppressalis</text>
      </annotation>
      <annotation id="10">
        <infon key="identifier"></infon>
        <infon key="type">Gene</infon>
        <infon key="updated_at">1980-01-01T00:00:00Z</infon>
        <location offset="514" length="7"/>
        <text>CsGluCl</text>
      </annotation>
      <annotation id="11">
        <infon key="identifier"></infon>
        <infon key="type">Gene</infon>
        <infon key="updated_at">1980-01-01T00:00:00Z</infon>
        <location offset="804" length="7"/>
        <text>CsGluCl</text>
      </annotation>
      <annotation id="12">
        <infon key="identifier">MESH:C442182</infon>
        <infon key="type">Chemical</infon>
        <infon key="updated_at">1980-01-01T00:00:00Z</infon>
        <location offset="812" length="1"/>
        <text>C</text>
      </annotation>
      <annotation id="13">
        <infon key="identifier"></infon>
        <infon key="type">Gene</infon>
        <infon key="updated_at">1980-01-01T00:00:00Z</infon>
        <location offset="1024" length="7"/>
        <text>CsGluCl</text>
      </annotation>
      <annotation id="16">
        <infon key="type">Gene</infon>
        <infon key="identifier"></infon>
        <infon key="annotator">5ef4bd7e0113</infon>
        <infon key="updated_at">2020-05-27T18:36:32Z</infon>
        <location offset="1247" length="5"/>
        <text>GluCl</text>
      </annotation>
    </passage>
  </document>
</collection>
